[
    {
        "id": "23",
        "question": "Этот знак означает:",
        "options": [
            "Игровая площадка",
            "Укладка асфальта",
            "Движение гольф-каров",
            "Движение сельскохозяйственной техники"
        ],
        "correct": "Движение гольф-каров",
        "image": "/sites/default/files/dorojnie-znaki-ssha-037-650x200.jpg",
        "description": ""
    },
    {
        "id": "28",
        "question": "Этим знаком обозначается:",
        "options": [
            "Госпиталь",
            "Пункт эвакуации при чрезвычайных происшествиях",
            "Детский лагерь",
            "Отель"
        ],
        "correct": "Отель",
        "image": "/sites/default/files/dorojnie-znaki-ssha-149-650x200.jpg",
        "description": ""
    },
    {
        "id": "11",
        "question": "Этот знак означает:",
        "options": [
            "Впереди резкий поворот",
            "Правая полоса заканчивается",
            "Дорога поворачивает налево",
            "Слияние трафика справа"
        ],
        "correct": "Дорога поворачивает налево",
        "image": "/sites/default/files/dorojnie-znaki-ssha-068-650x200.jpg",
        "description": ""
    },
    {
        "id": "9",
        "question": "Этот знак означает:",
        "options": [
            "Разрешено движение транспорта только больше 10 тонн",
            "Движение грузовиков запрещено",
            "Платный участок для транспорта тяжелее 10 тонн",
            "Запрещено движение транспорта тяжелее 10 тонн"
        ],
        "correct": "Запрещено движение транспорта тяжелее 10 тонн",
        "image": "/sites/default/files/dorojnie-znaki-ssha-168-650x200.jpg",
        "description": ""
    },
    {
        "id": "0",
        "question": "Этот знак означает:",
        "options": [
            "Впереди перегон домашнего скота",
            "Впереди движение сельскохозяйственной техники",
            "Впереди ферма",
            "Впереди зоопарк"
        ],
        "correct": "Впереди перегон домашнего скота",
        "image": "/sites/default/files/dorojnie-znaki-ssha-033-650x200.jpg",
        "description": ""
    },
    {
        "id": "32",
        "question": "Этот знак означает:",
        "options": [
            "Дорога закрыта",
            "Впереди перекресток",
            "Впереди железнодорожный переезд",
            "Железнодорожная станция"
        ],
        "correct": "Впереди железнодорожный переезд",
        "image": "/sites/default/files/dorojnie-znaki-ssha-098-650x200.jpg",
        "description": ""
    },
    {
        "id": "25",
        "question": "Этот знак означает:",
        "options": [
            "Впереди резкий поворот направо",
            "Впереди извилистая дорога",
            "Слияние трафика слева",
            "Левая полоса заканчивается"
        ],
        "correct": "Впереди резкий поворот направо",
        "image": "/sites/default/files/dorojnie-znaki-ssha-060-650x200.jpg",
        "description": ""
    },
    {
        "id": "6",
        "question": "Этот знак означает:",
        "options": [
            "Дорога занесена снегом",
            "Впереди национальный парк",
            "Впереди уборка снега",
            "Впереди движение снегоходов"
        ],
        "correct": "Впереди движение снегоходов",
        "image": "/sites/default/files/dorojnie-znaki-ssha-036-650x200.jpg",
        "description": ""
    },
    {
        "id": "38",
        "question": "Этот знак означает:",
        "options": [
            "Дорогу справа пересекает река",
            "Дорога справа закрыта",
            "Параллельно вашему пути проходит железная дорога",
            "Впереди железная дорога"
        ],
        "correct": "Параллельно вашему пути проходит железная дорога",
        "image": "/sites/default/files/dorojnie-znaki-ssha-022-650x200.jpg",
        "description": ""
    },
    {
        "id": "16",
        "question": "Этот знак означает:",
        "options": [
            "Держитесь левее",
            "Впереди разделитель шоссе",
            "Впереди извилистая дорога",
            "Правая полоса заканчивается"
        ],
        "correct": "Держитесь левее",
        "image": "/sites/default/files/dorojnie-znaki-ssha-190-650x200.jpg",
        "description": ""
    },
    {
        "id": "24",
        "question": "Этот знак означает:",
        "options": [
            "Автомойка",
            "Паркомат",
            "Банкомат",
            "Заправка"
        ],
        "correct": "Заправка",
        "image": "/sites/default/files/dorojnie-znaki-ssha-146-650x200.jpg",
        "description": ""
    },
    {
        "id": "1",
        "question": "Этот знак означает:",
        "options": [
            "Участок, на котором запрещено обгонять, заканчивается",
            "Выезжайте на перекресток с осторожностью",
            "Впереди школьная зона, двигайтесь с осторожностью",
            "Обгонять другой транспорт запрещено"
        ],
        "correct": "Участок, на котором запрещено обгонять, заканчивается",
        "image": "/sites/default/files/dorojnie-znaki-ssha-166-650x200.jpg",
        "description": ""
    },
    {
        "id": "30",
        "question": "Этот знак означает:",
        "options": [
            "Впереди школьная зона",
            "Парковка запрещена",
            "Впереди скоростное шоссе",
            "Начало участка с двойными штрафами"
        ],
        "correct": "Начало участка с двойными штрафами",
        "image": "/sites/default/files/dorojnie-znaki-ssha-165-650x200.jpg",
        "description": ""
    },
    {
        "id": "22",
        "question": "Этот знак означает:",
        "options": [
            "Неверное направление",
            "Дорога закрыта",
            "Выезд с улицы отсутствует",
            "Впереди тупик"
        ],
        "correct": "Выезд с улицы отсутствует",
        "image": "/sites/default/files/dorojnie-znaki-ssha-049-650x200.jpg",
        "description": ""
    },
    {
        "id": "36",
        "question": "Этот знак означает:",
        "options": [
            "Дорога изгибается в правую сторону",
            "Слева объезд участка дорожных работ",
            "Левая полоса заканчивается",
            "Впереди резкий поворот"
        ],
        "correct": "Дорога изгибается в правую сторону",
        "image": "/sites/default/files/dorojnie-znaki-ssha-064-650x200.jpg",
        "description": ""
    },
    {
        "id": "27",
        "question": "Этот знак указывает на:",
        "options": [
            "Пункт оказания помощи при чрезвычайных происшествиях",
            "Пункты общепита",
            "Отель",
            "Кемпинг"
        ],
        "correct": "Пункты общепита",
        "image": "/sites/default/files/dorojnie-znaki-ssha-152-650x200.jpg",
        "description": ""
    },
    {
        "id": "8",
        "question": "Этот знак означает:",
        "options": [
            "Впереди резкий поворот",
            "Не садитесь за руль нетрезвыми",
            "Впереди извилистая дорога",
            "Скользкая дорога"
        ],
        "correct": "Скользкая дорога",
        "image": "/sites/default/files/dorojnie-znaki-ssha-043-650x200.jpg",
        "description": ""
    },
    {
        "id": "29",
        "question": "Этот знак указывает на:",
        "options": [
            "Библиотеку",
            "Пункт техосмотра транспорта",
            "Пункт проведения тестов DMV",
            "Информационные услуги для путешественников"
        ],
        "correct": "Информационные услуги для путешественников",
        "image": "/sites/default/files/dorojnie-znaki-ssha-147-650x200.jpg",
        "description": ""
    },
    {
        "id": "15",
        "question": "Этот знак означает:",
        "options": [
            "Рекомендованная скорость на повороте",
            "Справа шоссе № 25",
            "Съезд с шоссе через 25 миль",
            "Минимальная скорость на повороте"
        ],
        "correct": "Рекомендованная скорость на повороте",
        "image": "/sites/default/files/dorojnie-znaki-ssha-053-650x200.jpg",
        "description": ""
    },
    {
        "id": "18",
        "question": "Этот знак означает:",
        "options": [
            "Боковая дорога примыкает к шоссе",
            "Впереди тупик",
            "Впереди двухстороннее движение",
            "Впереди развилка (Y-образный перекресток)"
        ],
        "correct": "Впереди развилка (Y-образный перекресток)",
        "image": "/sites/default/files/dorojnie-znaki-ssha-067-650x200.jpg",
        "description": ""
    },
    {
        "id": "20",
        "question": "Вы находитесь в левой полосе. Увидев этот знак, вы должны:",
        "options": [
            "Развернуться",
            "Перестроиться в другую полосу",
            "Повернуть налево",
            "Повернуть налево или продолжить двигаться прямо"
        ],
        "correct": "Повернуть налево",
        "image": "/sites/default/files/dorojnie-znaki-ssha-167-650x200.jpg",
        "description": ""
    },
    {
        "id": "37",
        "question": "Этот знак означает:",
        "options": [
            "Станция замены машинного масла",
            "Автозаправка",
            "Рядом с шоссе проходит нефтепровод",
            "Недавно уложенный асфальт"
        ],
        "correct": "Недавно уложенный асфальт",
        "image": "/sites/default/files/dorojnie-znaki-ssha-135-650x200.jpg",
        "description": ""
    },
    {
        "id": "33",
        "question": "Этот знак означает:",
        "options": [
            "На дороге углубление",
            "Впереди грунтовая дорога",
            "Дорога закрыта",
            "Впереди &#039;лежачий полицейский&#039;"
        ],
        "correct": "Впереди &#039;лежачий полицейский&#039;",
        "image": "/sites/default/files/dorojnie-znaki-ssha-020-650x200.jpg",
        "description": ""
    },
    {
        "id": "34",
        "question": "Этот знак означает:",
        "options": [
            "Впереди школьная зона",
            "Впереди знак STOP",
            "Впереди знак &#039;Уступи дорогу&#039;",
            "Впереди изменение скоростного режима"
        ],
        "correct": "Впереди изменение скоростного режима",
        "image": "/sites/default/files/dorojnie-znaki-ssha-030-650x200.jpg",
        "description": ""
    },
    {
        "id": "39",
        "question": "Этим знаком обозначается:",
        "options": [
            "Резервация коренных американцев",
            "Холмистая местность",
            "Кемпинг или турбаза",
            "Остановка общественного транспорта"
        ],
        "correct": "Кемпинг или турбаза",
        "image": "/sites/default/files/dorojnie-znaki-ssha-150-650x200.jpg",
        "description": ""
    },
    {
        "id": "2",
        "question": "Этот знак означает:",
        "options": [
            "Впереди извилистая дорога",
            "Впереди резкий поворот налево и потом направо",
            "Правая полоса заканчивается, сместитесь левее",
            "Слияние трафика справа"
        ],
        "correct": "Впереди резкий поворот налево и потом направо",
        "image": "/sites/default/files/dorojnie-znaki-ssha-061-650x200.jpg",
        "description": ""
    },
    {
        "id": "17",
        "question": "Этот знак означает:",
        "options": [
            "Поворот направо на красный сигнал запрещен",
            "Впереди светофор",
            "Впереди знак &#039;Уступи дорогу&#039;",
            "Впереди нерегулируемый перекресток"
        ],
        "correct": "Впереди светофор",
        "image": "/sites/default/files/dorojnie-znaki-ssha-023-650x200.jpg",
        "description": ""
    },
    {
        "id": "3",
        "question": "Этот знак означает:",
        "options": [
            "К шоссе примыкает боковая дорога",
            "Слияние трафика справа",
            "Впереди тупик",
            "Впереди Т-образный перекресток"
        ],
        "correct": "К шоссе примыкает боковая дорога",
        "image": "/sites/default/files/dorojnie-znaki-ssha-063-650x200.jpg",
        "description": ""
    },
    {
        "id": "10",
        "question": "Этим символом на информационном щите обозначается:",
        "options": [
            "Железнодорожный переезд",
            "Трамвайные рельсы",
            "Вокзал или ж/д станция",
            "Стоянка трейлеров"
        ],
        "correct": "Вокзал или ж/д станция",
        "image": "/sites/default/files/dorojnie-znaki-ssha-142-650x200.jpg",
        "description": ""
    },
    {
        "id": "13",
        "question": "Этот знак означает:",
        "options": [
            "Палатка с едой",
            "Перевозка лошадей разрешена только в специальных прицепах",
            "Парковка для жилых трейлеров",
            "Мотель"
        ],
        "correct": "Парковка для жилых трейлеров",
        "image": "/sites/default/files/dorojnie-znaki-ssha-148-650x200.jpg",
        "description": ""
    },
    {
        "id": "26",
        "question": "Этот знак означает:",
        "options": [
            "Впереди светофор",
            "Впереди знак &#039;Уступите дорогу&#039;",
            "Впереди односторонняя улица",
            "Вы едете в неправильном направлении"
        ],
        "correct": "Впереди знак &#039;Уступите дорогу&#039;",
        "image": "/sites/default/files/dorojnie-znaki-ssha-024-650x200.jpg",
        "description": ""
    },
    {
        "id": "14",
        "question": "Этот знак означает:",
        "options": [
            "Боковую дорогу пересекает мост",
            "Боковую дорогу пересекают железнодорожные пути",
            "Впереди железная дорога",
            "Боковая дорога, примыкающая к шоссе, закрыта"
        ],
        "correct": "Боковую дорогу пересекают железнодорожные пути",
        "image": "/sites/default/files/dorojnie-znaki-ssha-021-650x200.jpg",
        "description": ""
    },
    {
        "id": "7",
        "question": "Этот знак означает:",
        "options": [
            "Рекомендованная скорость на повороте 35 миль/ч",
            "Справа шоссе № 35",
            "Через 35 миль поворот направо",
            "Дорога изгибается под углом 35 градусов"
        ],
        "correct": "Рекомендованная скорость на повороте 35 миль/ч",
        "image": "/sites/default/files/dorojnie-znaki-ssha-052-650x200.jpg",
        "description": ""
    },
    {
        "id": "35",
        "question": "Этот знак означает:",
        "options": [
            "Впереди ферма",
            "Движение гольф-каров",
            "Движение сельхозтехники",
            "Укладка асфальта"
        ],
        "correct": "Движение сельхозтехники",
        "image": "/sites/default/files/dorojnie-znaki-ssha-035-650x200.jpg",
        "description": ""
    },
    {
        "id": "4",
        "question": "Этот знак указывает:",
        "options": [
            "Номер маршрута",
            "Максимальную рекомендованную скорость",
            "Минимальную скорость на шоссе",
            "Расстояние до населенного пункта"
        ],
        "correct": "Максимальную рекомендованную скорость",
        "image": "/sites/default/files/dorojnie-znaki-ssha-084-650x200.jpg",
        "description": ""
    },
    {
        "id": "5",
        "question": "Этот знак означает:",
        "options": [
            "Разделитель на шоссе заканчивается",
            "Впереди шоссе с разделителем",
            "Впереди двухстороннее движение",
            "Правая полоса заканчивается"
        ],
        "correct": "Правая полоса заканчивается",
        "image": "/sites/default/files/dorojnie-znaki-ssha-076-650x200.jpg",
        "description": ""
    },
    {
        "id": "12",
        "question": "Этот знак указывает на:",
        "options": [
            "Пункт оказания экстренной медицинской помощи",
            "Маршрут для эвакуации во время урагана",
            "Аптека с дежурным фармацевтом",
            "Пункт сдачи крови"
        ],
        "correct": "Пункт оказания экстренной медицинской помощи",
        "image": "/sites/default/files/dorojnie-znaki-ssha-151-650x200.jpg",
        "description": ""
    },
    {
        "id": "21",
        "question": "Этот знак означает:",
        "options": [
            "Неверное направление, вы должны развернуться",
            "Развороты и повороты налево запрещены",
            "Слияние трафика справа",
            "Въезд запрещен"
        ],
        "correct": "Развороты и повороты налево запрещены",
        "image": "/sites/default/files/dorojnie-znaki-ssha-102-650x200.jpg",
        "description": ""
    },
    {
        "id": "19",
        "question": "Этот знак означает:",
        "options": [
            "Слияние трафика справа",
            "К шоссе добавляется дополнительная полоса",
            "Правая полоса заканчивается",
            "Впереди разделитель шоссе"
        ],
        "correct": "К шоссе добавляется дополнительная полоса",
        "image": "/sites/default/files/dorojnie-znaki-ssha-055-650x200.jpg",
        "description": ""
    },
    {
        "id": "31",
        "question": "Этот знак означает:",
        "options": [
            "Въезд запрещен",
            "Автостоп запрещен",
            "Повороты направо запрещены",
            "Движение пешеходов запрещено"
        ],
        "correct": "Автостоп запрещен",
        "image": "/sites/default/files/dorojnie-znaki-ssha-105-650x200.jpg",
        "description": ""
    }
]